qifa/__init__.py
qifa/cli.py
qifa-0.1.0.dist-info/METADATA
qifa-0.1.0.dist-info/WHEEL
qifa-0.1.0.dist-info/entry_points.txt
qifa-0.1.0.dist-info/top_level.txt
qifa-0.1.0.dist-info/RECORD
