Metadata-Version: 2.4
Name: qifa
Version: 0.1.0
Summary: flash-attn quick installer
Author: Voidful
License: BSD-3-Clause
Project-URL: Homepage, https://github.com/Dao-AILab/flash-attention
Requires-Python: >=3.8
Requires-Dist: requests>=2.31
Requires-Dist: packaging>=24.0
Requires-Dist: typing-extensions>=4.8
